src/__init__.py
src/tools/__init__.py
src/tools/api_discovery.py
src/tools/contexts.py
src/tools/describe.py
src/tools/diagnosis.py
src/tools/events.py
src/tools/metrics.py
src/tools/namespaces.py
src/tools/node_management.py
src/tools/nodes.py
src/tools/pod_operations.py
src/tools/pods.py
src/tools/resource_management.py
src/tools/resources.py
src/tools/rollouts.py
src/tools/scaling.py
src/tools/workload_management.py
src/utils/__init__.py
src/utils/k8s_client.py
mseep_k8s_multicluster_mcp-1.0.0.dist-info/METADATA
mseep_k8s_multicluster_mcp-1.0.0.dist-info/WHEEL
mseep_k8s_multicluster_mcp-1.0.0.dist-info/top_level.txt
mseep_k8s_multicluster_mcp-1.0.0.dist-info/RECORD
